{"assets/images/LOGO.jpeg":["assets/images/LOGO.jpeg"],"assets/images/LOGO.png":["assets/images/LOGO.png"],"assets/images/P1.png":["assets/images/P1.png"],"assets/images/P2.png":["assets/images/P2.png"],"assets/images/P3.png":["assets/images/P3.png"],"assets/images/P4.png":["assets/images/P4.png"],"assets/sounds/Music1.mp3":["assets/sounds/Music1.mp3"],"assets/sounds/Music2.mp3":["assets/sounds/Music2.mp3"],"assets/sounds/Music3.mp3":["assets/sounds/Music3.mp3"],"assets/sounds/Music4.mp3":["assets/sounds/Music4.mp3"],"assets/sounds/Music5.mp3":["assets/sounds/Music5.mp3"],"assets/videos/ArmsPump.mp4":["assets/videos/ArmsPump.mp4"],"assets/videos/BackBuilder.mp4":["assets/videos/BackBuilder.mp4"],"assets/videos/CardioBalance.mp4":["assets/videos/CardioBalance.mp4"],"assets/videos/ChestPower.mp4":["assets/videos/ChestPower.mp4"],"assets/videos/CoreStability.mp4":["assets/videos/CoreStability.mp4"],"assets/videos/FatBlaster.mp4":["assets/videos/FatBlaster.mp4"],"assets/videos/FullBodyCardio.mp4":["assets/videos/FullBodyCardio.mp4"],"assets/videos/FullBodyMix.mp4":["assets/videos/FullBodyMix.mp4"],"assets/videos/HIITBurn.mp4":["assets/videos/HIITBurn.mp4"],"assets/videos/LegsShred.mp4":["assets/videos/LegsShred.mp4"],"assets/videos/LegsStrength.mp4":["assets/videos/LegsStrength.mp4"],"assets/videos/LightStrength.mp4":["assets/videos/LightStrength.mp4"],"assets/videos/MobilityFlow.mp4":["assets/videos/MobilityFlow.mp4"],"assets/videos/ShouldersCut.mp4":["assets/videos/ShouldersCut.mp4"],"assets/videos/ShouldersPress.mp4":["assets/videos/ShouldersPress.mp4"],"packages/cupertino_icons/assets/CupertinoIcons.ttf":["packages/cupertino_icons/assets/CupertinoIcons.ttf"]}